{
  "version": "7",
  "dialect": "sqlite",
  "id": "09bcac06-b28a-41c2-bd4a-bef945b966e6",
  "prevIds": ["00000000-0000-0000-0000-000000000000"],
  "ddl": [
    {
      "name": "chat_messages",
      "entityType": "tables"
    },
    {
      "name": "chat_sessions",
      "entityType": "tables"
    },
    {
      "type": "text",
      "notNull": false,
      "autoincrement": false,
      "default": null,
      "generated": null,
      "name": "id",
      "entityType": "columns",
      "table": "chat_messages"
    },
    {
      "type": "text",
      "notNull": true,
      "autoincrement": false,
      "default": null,
      "generated": null,
      "name": "session_id",
      "entityType": "columns",
      "table": "chat_messages"
    },
    {
      "type": "text",
      "notNull": true,
      "autoincrement": false,
      "default": null,
      "generated": null,
      "name": "role",
      "entityType": "columns",
      "table": "chat_messages"
    },
    {
      "type": "text",
      "notNull": true,
      "autoincrement": false,
      "default": null,
      "generated": null,
      "name": "parts_json",
      "entityType": "columns",
      "table": "chat_messages"
    },
    {
      "type": "text",
      "notNull": true,
      "autoincrement": false,
      "default": "'done'",
      "generated": null,
      "name": "status",
      "entityType": "columns",
      "table": "chat_messages"
    },
    {
      "type": "integer",
      "notNull": true,
      "autoincrement": false,
      "default": null,
      "generated": null,
      "name": "sequence",
      "entityType": "columns",
      "table": "chat_messages"
    },
    {
      "type": "integer",
      "notNull": true,
      "autoincrement": false,
      "default": null,
      "generated": null,
      "name": "created_at",
      "entityType": "columns",
      "table": "chat_messages"
    },
    {
      "type": "integer",
      "notNull": true,
      "autoincrement": false,
      "default": null,
      "generated": null,
      "name": "updated_at",
      "entityType": "columns",
      "table": "chat_messages"
    },
    {
      "type": "text",
      "notNull": false,
      "autoincrement": false,
      "default": null,
      "generated": null,
      "name": "error_text",
      "entityType": "columns",
      "table": "chat_messages"
    },
    {
      "type": "text",
      "notNull": false,
      "autoincrement": false,
      "default": null,
      "generated": null,
      "name": "metadata",
      "entityType": "columns",
      "table": "chat_messages"
    },
    {
      "type": "text",
      "notNull": false,
      "autoincrement": false,
      "default": null,
      "generated": null,
      "name": "id",
      "entityType": "columns",
      "table": "chat_sessions"
    },
    {
      "type": "text",
      "notNull": true,
      "autoincrement": false,
      "default": null,
      "generated": null,
      "name": "title",
      "entityType": "columns",
      "table": "chat_sessions"
    },
    {
      "type": "text",
      "notNull": true,
      "autoincrement": false,
      "default": "'active'",
      "generated": null,
      "name": "status",
      "entityType": "columns",
      "table": "chat_sessions"
    },
    {
      "type": "integer",
      "notNull": true,
      "autoincrement": false,
      "default": null,
      "generated": null,
      "name": "created_at",
      "entityType": "columns",
      "table": "chat_sessions"
    },
    {
      "type": "integer",
      "notNull": true,
      "autoincrement": false,
      "default": null,
      "generated": null,
      "name": "updated_at",
      "entityType": "columns",
      "table": "chat_sessions"
    },
    {
      "type": "integer",
      "notNull": false,
      "autoincrement": false,
      "default": null,
      "generated": null,
      "name": "last_message_at",
      "entityType": "columns",
      "table": "chat_sessions"
    },
    {
      "type": "text",
      "notNull": false,
      "autoincrement": false,
      "default": null,
      "generated": null,
      "name": "model",
      "entityType": "columns",
      "table": "chat_sessions"
    },
    {
      "type": "text",
      "notNull": false,
      "autoincrement": false,
      "default": null,
      "generated": null,
      "name": "system_prompt",
      "entityType": "columns",
      "table": "chat_sessions"
    },
    {
      "type": "text",
      "notNull": false,
      "autoincrement": false,
      "default": null,
      "generated": null,
      "name": "summary",
      "entityType": "columns",
      "table": "chat_sessions"
    },
    {
      "type": "text",
      "notNull": false,
      "autoincrement": false,
      "default": null,
      "generated": null,
      "name": "metadata",
      "entityType": "columns",
      "table": "chat_sessions"
    },
    {
      "columns": ["session_id"],
      "tableTo": "chat_sessions",
      "columnsTo": ["id"],
      "onUpdate": "NO ACTION",
      "onDelete": "CASCADE",
      "nameExplicit": false,
      "name": "fk_chat_messages_session_id_chat_sessions_id_fk",
      "entityType": "fks",
      "table": "chat_messages"
    },
    {
      "columns": ["id"],
      "nameExplicit": false,
      "name": "chat_messages_pk",
      "table": "chat_messages",
      "entityType": "pks"
    },
    {
      "columns": ["id"],
      "nameExplicit": false,
      "name": "chat_sessions_pk",
      "table": "chat_sessions",
      "entityType": "pks"
    },
    {
      "columns": [
        {
          "value": "session_id",
          "isExpression": false
        },
        {
          "value": "sequence",
          "isExpression": false
        }
      ],
      "isUnique": true,
      "where": null,
      "origin": "manual",
      "name": "chat_messages_session_sequence_uidx",
      "entityType": "indexes",
      "table": "chat_messages"
    },
    {
      "columns": [
        {
          "value": "session_id",
          "isExpression": false
        },
        {
          "value": "created_at",
          "isExpression": false
        }
      ],
      "isUnique": false,
      "where": null,
      "origin": "manual",
      "name": "chat_messages_session_created_at_idx",
      "entityType": "indexes",
      "table": "chat_messages"
    },
    {
      "columns": [
        {
          "value": "updated_at",
          "isExpression": false
        }
      ],
      "isUnique": false,
      "where": null,
      "origin": "manual",
      "name": "chat_sessions_updated_at_idx",
      "entityType": "indexes",
      "table": "chat_sessions"
    },
    {
      "columns": [
        {
          "value": "last_message_at",
          "isExpression": false
        }
      ],
      "isUnique": false,
      "where": null,
      "origin": "manual",
      "name": "chat_sessions_last_message_at_idx",
      "entityType": "indexes",
      "table": "chat_sessions"
    }
  ],
  "renames": []
}
